setup.py
kaczmarz/__init__.py
kaczmarz/linsys.py
kaczmarz/plot.py
kaczmarz/rowitr.py
kaczmarz/util.py
kaczmarz.egg-info/PKG-INFO
kaczmarz.egg-info/SOURCES.txt
kaczmarz.egg-info/dependency_links.txt
kaczmarz.egg-info/requires.txt
kaczmarz.egg-info/top_level.txt
kaczmarz.egg-info/zip-safe